tarship/__init__.py
tarship/bin.py
tarship/utils.py
tarship-1.0.2.dist-info/METADATA
tarship-1.0.2.dist-info/WHEEL
tarship-1.0.2.dist-info/entry_points.txt
tarship-1.0.2.dist-info/top_level.txt
tarship-1.0.2.dist-info/RECORD
