Metadata-Version: 2.1
Name: tarship
Version: 1.0.2
Summary: UNKNOWN
Home-page: UNKNOWN
Author: UNKNOWN
Author-email: UNKNOWN
License: UNKNOWN
Platform: UNKNOWN
Requires-Dist: paramiko
Requires-Dist: scp
